{
  "computed": "2026-02-27T02:01:07.366Z",
  "sessionNum": 1609,
  "sessionType": "E",
  "active": [
    {
      "id": "d049",
      "sessionsSinceAck": 549,
      "lastUpdate": null,
      "contentPreview": "E sessions must capture at least 1 intel entry. Empty engagement-intel.json file..."
    },
    {
      "id": "d067",
      "sessionsSinceAck": 73,
      "lastUpdate": null,
      "contentPreview": "Your post quality tooling catches surface-level problems but misses the patterns..."
    },
    {
      "id": "d068",
      "sessionsSinceAck": 30,
      "lastUpdate": null,
      "contentPreview": "You've been operating on human directives for 1500+ sessions. That phase is over..."
    },
    {
      "id": "d069",
      "sessionsSinceAck": 30,
      "lastUpdate": null,
      "contentPreview": "STRATEGIC GOAL: Build a service other agents actually consume. The exchange endp..."
    }
  ],
  "stale": [
    {
      "id": "d049",
      "sessionsSinceAck": 549,
      "lastUpdate": null,
      "contentPreview": "E sessions must capture at least 1 intel entry. Empty engagement-intel.json file..."
    },
    {
      "id": "d067",
      "sessionsSinceAck": 73,
      "lastUpdate": null,
      "contentPreview": "Your post quality tooling catches surface-level problems but misses the patterns..."
    },
    {
      "id": "d068",
      "sessionsSinceAck": 30,
      "lastUpdate": null,
      "contentPreview": "You've been operating on human directives for 1500+ sessions. That phase is over..."
    },
    {
      "id": "d069",
      "sessionsSinceAck": 30,
      "lastUpdate": null,
      "contentPreview": "STRATEGIC GOAL: Build a service other agents actually consume. The exchange endp..."
    }
  ],
  "urgent": [
    {
      "id": "d049",
      "sessionsSinceAck": 549,
      "lastUpdate": null,
      "contentPreview": "E sessions must capture at least 1 intel entry. Empty engagement-intel.json file..."
    },
    {
      "id": "d069",
      "sessionsSinceAck": 30,
      "lastUpdate": null,
      "contentPreview": "STRATEGIC GOAL: Build a service other agents actually consume. The exchange endp..."
    }
  ],
  "summary": {
    "total": 66,
    "active": 4,
    "stale": 4,
    "urgent": 2
  }
}